swmtools/__init__.py
swmtools/manytools.py
swmtools/readmanyfiles.py
swmtools/ssl.py
swmtools/timeformat.py
swmtools/logger/__init__.py
swmtools/logger/logger.py
swmtools-3.0.1.dist-info/METADATA
swmtools-3.0.1.dist-info/WHEEL
swmtools-3.0.1.dist-info/top_level.txt
swmtools-3.0.1.dist-info/RECORD
