Metadata-Version: 2.1
Name: swmtools
Version: 3.0.1
Summary: util tools for daily dev
Home-page: https://github.com/Octoberr/swmpackages
Author: october
Author-email: sepjudy@gmail.com
License: UNKNOWN
Project-URL: Source, https://github.com/Octoberr/swmpackages
Keywords: daily work setup tools
Platform: UNKNOWN
Classifier: Development Status :: 3 - Alpha
Classifier: Intended Audience :: Developers
Classifier: Topic :: Software Development :: Build Tools
Classifier: Programming Language :: Python :: 3.6
Classifier: Programming Language :: Python :: 3.7
Classifier: Programming Language :: Python :: 3.8
Classifier: Programming Language :: Python :: 3.9
Requires-Dist: xlrd (>=1.2.0)
Requires-Dist: pytz (>=2021.1)
